ovos_vad_plugin_silero/__init__.py
ovos_vad_plugin_silero/silero_vad.onnx
ovos_vad_plugin_silero/version.py
ovos_vad_plugin_silero-0.1.0.dist-info/licenses/LICENSE
ovos_vad_plugin_silero-0.1.0.dist-info/METADATA
ovos_vad_plugin_silero-0.1.0.dist-info/WHEEL
ovos_vad_plugin_silero-0.1.0.dist-info/entry_points.txt
ovos_vad_plugin_silero-0.1.0.dist-info/top_level.txt
ovos_vad_plugin_silero-0.1.0.dist-info/zip-safe
ovos_vad_plugin_silero-0.1.0.dist-info/RECORD
