Metadata-Version: 2.4
Name: ovos-vad-plugin-silero
Version: 0.1.0
Summary: silero VAD plugin for OpenVoiceOS
Home-page: https://github.com/OpenVoiceOS/ovos-vad-plugin-silero
Author: JarbasAi
Author-email: jarbasai@mailfence.com
License: Apache-2.0
Keywords: mycroft plugin VAD OVOS OpenVoiceOS
Classifier: Development Status :: 3 - Alpha
Classifier: Intended Audience :: Developers
Classifier: Topic :: Text Processing :: Linguistic
Classifier: License :: OSI Approved :: Apache Software License
Classifier: Programming Language :: Python :: 2
Classifier: Programming Language :: Python :: 2.7
Classifier: Programming Language :: Python :: 3
Classifier: Programming Language :: Python :: 3.0
Classifier: Programming Language :: Python :: 3.1
Classifier: Programming Language :: Python :: 3.2
Classifier: Programming Language :: Python :: 3.3
Classifier: Programming Language :: Python :: 3.4
Classifier: Programming Language :: Python :: 3.5
Classifier: Programming Language :: Python :: 3.6
License-File: LICENSE
Requires-Dist: ovos-plugin-manager<3.0.0,>=2.1.0a1
Requires-Dist: onnxruntime
Requires-Dist: numpy<3.0.0
Dynamic: author
Dynamic: author-email
Dynamic: classifier
Dynamic: description
Dynamic: description-content-type
Dynamic: home-page
Dynamic: keywords
Dynamic: license
Dynamic: license-file
Dynamic: requires-dist
Dynamic: summary
